GIFgraph/__init__.py
GIFgraph/change_log.txt
GIFgraph/doggy.gif
GIFgraph/graph_icon.png
GIFgraph-0.1.2.dist-info/License.txt
GIFgraph-0.1.2.dist-info/METADATA
GIFgraph-0.1.2.dist-info/WHEEL
GIFgraph-0.1.2.dist-info/top_level.txt
GIFgraph-0.1.2.dist-info/RECORD
