Metadata-Version: 2.1
Name: GIFgraph
Version: 0.1.2
Summary: GIFgraph provides animated data visuals in the form of GIFs.
Home-page: https://github.com/henrysrtaylor/GIFgraph
Author: Henry Taylor
Author-email: henrysrtaylor@gmail.com
License: LICENSE.txt
Platform: UNKNOWN
Requires-Dist: pillow
Requires-Dist: glob2
Requires-Dist: matplotlib
Requires-Dist: pyglet
Requires-Dist: numpy
